README.md
setup.py
markmin/__init__.py
markmin/markmin2html.py
markmin/markmin2latex.py
markmin/markmin2pdf.py
markmin.egg-info/PKG-INFO
markmin.egg-info/SOURCES.txt
markmin.egg-info/dependency_links.txt
markmin.egg-info/not-zip-safe
markmin.egg-info/top_level.txt